datalineagepy/__init__.py
datalineagepy/alerting/integrations.py
datalineagepy/benchmarks/__init__.py
datalineagepy/benchmarks/competitive_analysis.py
datalineagepy/benchmarks/memory_profiler.py
datalineagepy/benchmarks/performance_benchmarks.py
datalineagepy/collaboration/realtime_collaboration.py
datalineagepy/compliance/__init__.py
datalineagepy/compliance/audit.py
datalineagepy/compliance/framework.py
datalineagepy/compliance/gdpr.py
datalineagepy/compliance/hipaa.py
datalineagepy/compliance/sox.py
datalineagepy/connectors/__init__.py
datalineagepy/connectors/custom_connector_sdk.py
datalineagepy/connectors/cloud/s3_connector.py
datalineagepy/connectors/database/__init__.py
datalineagepy/connectors/database/mysql_connector.py
datalineagepy/connectors/database/postgresql_connector.py
datalineagepy/connectors/database/sqlite_connector.py
datalineagepy/connectors/streaming/__init__.py
datalineagepy/connectors/streaming/kafka_connector.py
datalineagepy/core/__init__.py
datalineagepy/core/analytics.py
datalineagepy/core/dataframe_wrapper.py
datalineagepy/core/edges.py
datalineagepy/core/lineage_versioning.py
datalineagepy/core/nodes.py
datalineagepy/core/operations.py
datalineagepy/core/performance.py
datalineagepy/core/serialization.py
datalineagepy/core/tracker.py
datalineagepy/core/validation.py
datalineagepy/edge/__init__.py
datalineagepy/edge/edge_node.py
datalineagepy/governance/__init__.py
datalineagepy/governance/classification_engine.py
datalineagepy/governance/stewardship_manager.py
datalineagepy/infrastructure/__init__.py
datalineagepy/infrastructure/high_availability/__init__.py
datalineagepy/infrastructure/high_availability/circuit_breaker.py
datalineagepy/infrastructure/high_availability/health_checker.py
datalineagepy/infrastructure/monitoring/__init__.py
datalineagepy/infrastructure/monitoring/alert_manager.py
datalineagepy/infrastructure/monitoring/dashboard.py
datalineagepy/infrastructure/monitoring/exporters.py
datalineagepy-3.0.3.dist-info/licenses/LICENSE
datalineagepy-3.0.3.dist-info/METADATA
datalineagepy-3.0.3.dist-info/WHEEL
datalineagepy-3.0.3.dist-info/entry_points.txt
datalineagepy-3.0.3.dist-info/top_level.txt
datalineagepy-3.0.3.dist-info/RECORD
