Metadata-Version: 2.4
Name: datalineagepy
Version: 3.0.3
Summary: Enterprise-grade Python data lineage tracking library with automatic pandas integration, perfect memory optimization, and comprehensive visualization capabilities.
Author-email: Arbaz Nazir <arbaznazir4@gmail.com>
Maintainer-email: Arbaz Nazir <arbaznazir4@gmail.com>
License: MIT
Project-URL: Homepage, https://github.com/Arbaznazir/DataLineagePy
Project-URL: Documentation, https://github.com/Arbaznazir/DataLineagePy/tree/main/docs
Project-URL: Repository, https://github.com/Arbaznazir/DataLineagePy
Project-URL: Bug Tracker, https://github.com/Arbaznazir/DataLineagePy/issues
Project-URL: Feature Requests, https://github.com/Arbaznazir/DataLineagePy/discussions
Project-URL: Release Notes, https://github.com/Arbaznazir/DataLineagePy/blob/main/CHANGELOG.md
Project-URL: Source Code, https://github.com/Arbaznazir/DataLineagePy
Project-URL: Download, https://pypi.org/project/datalineagepy/
Project-URL: User Guide, https://github.com/Arbaznazir/DataLineagePy/tree/main/docs/user-guide
Project-URL: API Reference, https://github.com/Arbaznazir/DataLineagePy/tree/main/docs/api
Project-URL: Quick Start, https://github.com/Arbaznazir/DataLineagePy/blob/main/docs/quickstart.md
Project-URL: Installation Guide, https://github.com/Arbaznazir/DataLineagePy/blob/main/docs/installation.md
Project-URL: Examples, https://github.com/Arbaznazir/DataLineagePy/tree/main/examples
Project-URL: FAQ, https://github.com/Arbaznazir/DataLineagePy/blob/main/docs/faq.md
Keywords: data-lineage,pandas,data-tracking,etl,data-pipeline,data-governance,visualization,enterprise,analytics,ml-ops
Classifier: Development Status :: 5 - Production/Stable
Classifier: Intended Audience :: Developers
Classifier: Intended Audience :: Science/Research
Classifier: Intended Audience :: Information Technology
Classifier: Intended Audience :: Financial and Insurance Industry
Classifier: Topic :: Software Development :: Libraries :: Python Modules
Classifier: Topic :: Scientific/Engineering :: Information Analysis
Classifier: Topic :: Database
Classifier: Topic :: Documentation
Classifier: Topic :: Office/Business
Classifier: Topic :: Utilities
Classifier: Typing :: Typed
Requires-Python: >=3.8
License-File: LICENSE
Requires-Dist: pandas>=1.3.0
Requires-Dist: numpy>=1.21.0
Requires-Dist: matplotlib>=3.3.0
Requires-Dist: networkx>=2.6.0
Requires-Dist: tqdm>=4.60.0
Requires-Dist: psutil>=5.8.0
Provides-Extra: viz
Requires-Dist: plotly>=5.0.0; extra == "viz"
Requires-Dist: graphviz>=0.16; extra == "viz"
Requires-Dist: seaborn>=0.11.0; extra == "viz"
Requires-Dist: bokeh>=2.3.0; extra == "viz"
Provides-Extra: dev
Requires-Dist: pytest>=7.0.0; extra == "dev"
Requires-Dist: pytest-cov>=3.0.0; extra == "dev"
Requires-Dist: black>=22.0.0; extra == "dev"
Requires-Dist: flake8>=4.0.0; extra == "dev"
Requires-Dist: mypy>=0.950; extra == "dev"
Requires-Dist: pre-commit>=2.17.0; extra == "dev"
Requires-Dist: sphinx>=4.0.0; extra == "dev"
Requires-Dist: sphinx-rtd-theme>=1.0.0; extra == "dev"
Requires-Dist: twine>=4.0.0; extra == "dev"
Requires-Dist: build>=0.8.0; extra == "dev"
Provides-Extra: test
Requires-Dist: pytest>=7.0.0; extra == "test"
Requires-Dist: pytest-cov>=3.0.0; extra == "test"
Requires-Dist: pytest-xdist>=2.5.0; extra == "test"
Requires-Dist: pytest-benchmark>=3.4.0; extra == "test"
Requires-Dist: hypothesis>=6.0.0; extra == "test"
Requires-Dist: factory-boy>=3.2.0; extra == "test"
Provides-Extra: docs
Requires-Dist: sphinx>=4.0.0; extra == "docs"
Requires-Dist: sphinx-rtd-theme>=1.0.0; extra == "docs"
Requires-Dist: myst-parser>=0.17.0; extra == "docs"
Requires-Dist: sphinx-autodoc-typehints>=1.17.0; extra == "docs"
Requires-Dist: sphinx-copybutton>=0.5.0; extra == "docs"
Provides-Extra: performance
Requires-Dist: memory-profiler>=0.60.0; extra == "performance"
Requires-Dist: line-profiler>=3.5.0; extra == "performance"
Requires-Dist: py-spy>=0.3.0; extra == "performance"
Requires-Dist: scalene>=1.5.0; extra == "performance"
Provides-Extra: enterprise
Requires-Dist: cryptography>=3.4.0; extra == "enterprise"
Requires-Dist: sqlalchemy>=1.4.0; extra == "enterprise"
Requires-Dist: redis>=4.0.0; extra == "enterprise"
Requires-Dist: celery>=5.2.0; extra == "enterprise"
Requires-Dist: prometheus-client>=0.14.0; extra == "enterprise"
Provides-Extra: cloud
Requires-Dist: boto3>=1.20.0; extra == "cloud"
Requires-Dist: azure-storage-blob>=12.8.0; extra == "cloud"
Requires-Dist: google-cloud-storage>=2.0.0; extra == "cloud"
Requires-Dist: apache-airflow>=2.3.0; extra == "cloud"
Provides-Extra: ml
Requires-Dist: scikit-learn>=1.0.0; extra == "ml"
Requires-Dist: xgboost>=1.5.0; extra == "ml"
Requires-Dist: lightgbm>=3.3.0; extra == "ml"
Requires-Dist: tensorflow>=2.8.0; extra == "ml"
Requires-Dist: torch>=1.11.0; extra == "ml"
Provides-Extra: all
Requires-Dist: datalineagepy[cloud,dev,docs,enterprise,ml,performance,test,viz]; extra == "all"
Dynamic: license-file
